time_granularity/__init__.py
time_granularity/time_granularity.py
time_granularity-1.1.dist-info/METADATA
time_granularity-1.1.dist-info/WHEEL
time_granularity-1.1.dist-info/top_level.txt
time_granularity-1.1.dist-info/RECORD
